cli.py
errors.py
main.py
console/__init__.py
console/completions.py
console/loop.py
console/utils.py
db/__init__.py
db/driver.py
db/query.py
domain/__init__.py
domain/auth.py
domain/behaviors.py
domain/output.py
domain/servicekind.py
graphc-0.1.3.dist-info/licenses/LICENSE
utils/__init__.py
utils/dirs.py
utils/output.py
graphc-0.1.3.dist-info/METADATA
graphc-0.1.3.dist-info/WHEEL
graphc-0.1.3.dist-info/entry_points.txt
graphc-0.1.3.dist-info/top_level.txt
graphc-0.1.3.dist-info/RECORD
