Metadata-Version: 2.4
Name: graphc
Version: 0.1.3
Summary: query graph databases via an interactive console
License-Expression: MIT
Project-URL: Homepage, https://tools.dhruvs.space/graphc/
Project-URL: Repository, https://github.com/dhth/graphc
Project-URL: Issues, https://github.com/dhth/graphc/issues
Keywords: neo4j,neptune,graph,database,cypher,console,cli
Classifier: Development Status :: 4 - Beta
Classifier: Environment :: Console
Classifier: Intended Audience :: Developers
Classifier: Operating System :: OS Independent
Classifier: Programming Language :: Python :: 3.12
Classifier: Topic :: Database
Classifier: Topic :: Utilities
Requires-Python: >=3.12
License-File: LICENSE
Requires-Dist: boto3>=1.39.14
Requires-Dist: neo4j>=5.28.1
Requires-Dist: pandas>=2.3.1
Requires-Dist: platformdirs>=4.3.8
Requires-Dist: prompt-toolkit>=3.0.51
Requires-Dist: rich>=14.1.0
Dynamic: license-file
